README
README.md
setup.py
filabel/__init__.py
filabel/main.py
filabel.egg-info/PKG-INFO
filabel.egg-info/SOURCES.txt
filabel.egg-info/dependency_links.txt
filabel.egg-info/entry_points.txt
filabel.egg-info/requires.txt
filabel.egg-info/top_level.txt