Metadata-Version: 1.0
Name: filabel
Version: 0.1.2
Summary: Label files quickly for image classification
Home-page: https://github.com/paulfitz/filabel
Author: Paul Fitzpatrick
Author-email: paulfitz@alum.mit.edu
License: UNKNOWN
Platform: UNKNOWN
